README.rst
xact/_meta/conftest.py
xact/_meta/spec_xact.py
xact/cfg/__init__.py
xact/cfg/_meta/conftest.py
xact/cfg/_meta/spec_xact_cfg.py
xact/cfg/_meta/spec_xact_cfg_builder.py
xact/cfg/_meta/spec_xact_cfg_edge.py
xact/cfg/_meta/spec_xact_cfg_load.py
xact/cfg/_meta/spec_xact_cfg_override.py
xact/cfg/_meta/spec_xact_cfg_util.py
xact/cfg/_meta/spec_xact_cfg_validate.py
xact/cfg/builder.py
xact/cfg/data/__init__.py
xact/cfg/data/_meta/conftest.py
xact/cfg/data/_meta/spec_xact_cfg_data.py
xact/cfg/data/_meta/spec_xact_cfg_data_atomic_types.py
xact/cfg/data/_meta/spec_xact_cfg_data_gap_table.py
xact/cfg/data/atomic_types.py
xact/cfg/data/gap_table.py
xact/cfg/edge.py
xact/cfg/exception.py
xact/cfg/load.py
xact/cfg/override.py
xact/cfg/util.py
xact/cfg/validate.py
xact/cli/__init__.py
xact/cli/_meta/conftest.py
xact/cli/_meta/spec_xact_cli.py
xact/cli/_meta/spec_xact_cli_command.py
xact/cli/_meta/spec_xact_cli_util.py
xact/cli/command.py
xact/cli/util.py
xact/gen/__init__.py
xact/gen/_meta/spec_xact_gen.py
xact/gen/_meta/spec_xact_gen_python.py
xact/gen/python.py
xact/host/__init__.py
xact/host/_meta/spec_xact_host.py
xact/host/_meta/spec_xact_host_remote.py
xact/host/util.py
xact/log/__init__.py
xact/node/__init__.py
xact/node/_meta/spec_xact_node.py
xact/proc/__init__.py
xact/proc/_meta/spec_xact_proc.py
xact/queue/__init__.py
xact/queue/_meta/spec_xact_queue.py
xact/sys/__init__.py
xact/sys/_meta/spec_xact_sys.py
xact/sys/_meta/spec_xact_sys_exception.py
xact/sys/exception.py
xact/sys/orchestration/__init__.py
xact/sys/orchestration/ansible.py
xact/util/__init__.py
xact/util/_meta/spec_xact_util.py
xact/util/_meta/spec_xact_util_serialization.py
xact/util/serialization.py
xact-0.0.3.dev0.dist-info/entry_points.txt
xact-0.0.3.dev0.dist-info/LICENSE.txt
xact-0.0.3.dev0.dist-info/WHEEL
xact-0.0.3.dev0.dist-info/METADATA
xact-0.0.3.dev0.dist-info/RECORD
